mach2viz-0.0.3.dist-info/METADATA
mach2viz-0.0.3.dist-info/WHEEL
mach2viz-0.0.3.dist-info/entry_points.txt
mach2viz-0.0.3.dist-info/licenses/LICENSE
mach2viz/__init__.py
mach2viz/run.py
mach2viz-0.0.3.dist-info/RECORD
