Metadata-Version: 2.1
Name: mach2viz
Version: 0.0.3
Summary: Online interactive visualizer for Migration Analysis of Clonal History 2 (MACH2)
Keywords: Computational biology Bioinformatics Cancer Metastasis Phylogeny
Author-Email: Vikram Ramavarapu <vikramr2@illinois.edu>
License: MIT License
Classifier: Programming Language :: Python :: 3
Classifier: Operating System :: OS Independent
Classifier: Topic :: Scientific/Engineering :: Bio-Informatics
Project-URL: Homepage, https://github.com/elkebir-group/mach2-viz
Project-URL: Bug tracker, https://github.com/elkebir-group/mach2-viz/issues
Requires-Python: >=3.9
Requires-Dist: typer
Requires-Dist: selenium
